<?xml version="1.0"?>
<save_state>
	<window />
	<input />
	<AssetsManager />
	<textures />
	<audio />
	<scenemanager>
		<scenegameplay>
			<SceneGameplayInfo CurrentMap="6" Puzzle1Solved="false" Puzzle2Solved="false" Puzzle3Solved="false" />
			<Player x="163" y="134" />
		</scenegameplay>
	</scenemanager>
	<moduleCollisions />
	<guiManager />
	<entitymanager />
	<psmanager />
	<questmanager />
	<StatsManager />
	<map />
	<Hud />
	<Inventory />
	<debug />
	<renderer>
		<camera x="0" y="-42" />
	</renderer>
</save_state>
